{
  "total_blocks": 55,
  "source_result_json": "133_23-ГК-АР2_изм10_result.json",
  "blocks": [
    {
      "block_id": "7HRC-36NQ-W9N",
      "page": 5,
      "file": "block_7HRC-36NQ-W9N.png",
      "size_kb": 116.6,
      "crop_px": [
        239,
        183,
        7015,
        4227
      ],
      "render_size": [
        1629,
        975
      ],
      "block_type": "image",
      "ocr_label": "План осей подземной части в масштабе 1:200. Представляет собой разбивочную схему",
      "ocr_text_len": 1428
    },
    {
      "block_id": "6U6Q-3JDK-W7Y",
      "page": 5,
      "file": "block_6U6Q-3JDK-W7Y.png",
      "size_kb": 94.0,
      "crop_px": [
        533,
        4273,
        6453,
        8622
      ],
      "render_size": [
        1500,
        1104
      ],
      "block_type": "image",
      "ocr_label": "План осей надземной части в масштабе 1:200. Чертеж содержит схематичное располож",
      "ocr_text_len": 1556
    },
    {
      "block_id": "6KEX-FT79-AJX",
      "page": 5,
      "file": "block_6KEX-FT79-AJX.png",
      "size_kb": 200.5,
      "crop_px": [
        3477,
        8726,
        4747,
        9750
      ],
      "render_size": [
        1500,
        1214
      ],
      "block_type": "image",
      "ocr_label": "Схема застройки или генеральный план с обозначением контуров зданий, стилобата и",
      "ocr_text_len": 1439
    },
    {
      "block_id": "9CW3-M6U3-RRH",
      "page": 6,
      "file": "block_9CW3-M6U3-RRH.png",
      "size_kb": 161.0,
      "crop_px": [
        10691,
        59,
        12511,
        8360
      ],
      "render_size": [
        441,
        1997
      ],
      "block_type": "image",
      "ocr_label": "Спецификация перемычек -2-го этажа на отм. -7,650. Документация содержит маркиро",
      "ocr_text_len": 1781
    },
    {
      "block_id": "NTHY-VYQG-PKF",
      "page": 6,
      "file": "block_NTHY-VYQG-PKF.png",
      "size_kb": 130.2,
      "crop_px": [
        9327,
        7042,
        10275,
        8060
      ],
      "render_size": [
        1399,
        1500
      ],
      "block_type": "image",
      "ocr_label": "Фрагмент разреза лестничной клетки с указанием высотных отметок и межуровневых п",
      "ocr_text_len": 1059
    },
    {
      "block_id": "7RHP-GMVU-LEC",
      "page": 6,
      "file": "block_7RHP-GMVU-LEC.png",
      "size_kb": 113.2,
      "crop_px": [
        9109,
        8150,
        10315,
        9046
      ],
      "render_size": [
        1500,
        1120
      ],
      "block_type": "image",
      "ocr_label": "Фрагмент плана на отметке -6,150 в масштабе 1:100. Вероятно, относится к архитек",
      "ocr_text_len": 1088
    },
    {
      "block_id": "93CA-QTXN-MCG",
      "page": 6,
      "file": "block_93CA-QTXN-MCG.png",
      "size_kb": 79.1,
      "crop_px": [
        4737,
        8686,
        7853,
        9838
      ],
      "render_size": [
        1500,
        560
      ],
      "block_type": "image",
      "ocr_label": "Чертеж фрагмента стены (Вид 2) в масштабе 1:50, вероятно раздел АР или КЖ, показ",
      "ocr_text_len": 1622
    },
    {
      "block_id": "6T4K-7QUJ-JRD",
      "page": 6,
      "file": "block_6T4K-7QUJ-JRD.png",
      "size_kb": 191.4,
      "crop_px": [
        5071,
        7016,
        7053,
        8770
      ],
      "render_size": [
        1500,
        1329
      ],
      "block_type": "image",
      "ocr_label": "Чертеж фрагмента стены (Вид 1) с дверными проемами, выполненный на стадии РД. Из",
      "ocr_text_len": 1649
    },
    {
      "block_id": "7APV-C3VG-DL9",
      "page": 6,
      "file": "block_7APV-C3VG-DL9.png",
      "size_kb": 121.0,
      "crop_px": [
        2755,
        8924,
        4507,
        9860
      ],
      "render_size": [
        1500,
        808
      ],
      "block_type": "image",
      "ocr_label": "Фрагмент плана этажа на отметке -9,700. На чертеже изображены монолитные стены и",
      "ocr_text_len": 1340
    },
    {
      "block_id": "47KG-HEEY-4A7",
      "page": 6,
      "file": "block_47KG-HEEY-4A7.png",
      "size_kb": 730.8,
      "crop_px": [
        305,
        161,
        10657,
        7064
      ],
      "render_size": [
        2489,
        1661
      ],
      "block_type": "image",
      "ocr_label": "План расположения фундаментов и закладных деталей. Чертеж содержит маркировку от",
      "ocr_text_len": 1500
    },
    {
      "block_id": "ACDG-3JDQ-KAY",
      "page": 6,
      "file": "block_ACDG-3JDQ-KAY.png",
      "size_kb": 205.8,
      "crop_px": [
        10555,
        8852,
        11781,
        9782
      ],
      "render_size": [
        1500,
        1143
      ],
      "block_type": "image",
      "ocr_label": "Схема планировочной организации земельного участка (СПОЗУ) или ситуационный план",
      "ocr_text_len": 1507
    },
    {
      "block_id": "43DW-UGQ9-CDD",
      "page": 7,
      "file": "block_43DW-UGQ9-CDD.png",
      "size_kb": 143.9,
      "crop_px": [
        10575,
        8812,
        11769,
        9716
      ],
      "render_size": [
        1500,
        1141
      ],
      "block_type": "image",
      "ocr_label": "Фрагмент плана технического этажа (ПО №2) со схематичным отображением контуров п",
      "ocr_text_len": 1271
    },
    {
      "block_id": "6RGC-AU9X-KWY",
      "page": 7,
      "file": "block_6RGC-AU9X-KWY.png",
      "size_kb": 131.1,
      "crop_px": [
        11057,
        105,
        12805,
        4749
      ],
      "render_size": [
        568,
        1500
      ],
      "block_type": "image",
      "ocr_label": "Спецификация перемычек -1-го этажа на отм. -3,750. Ведомость включает эскизы сеч",
      "ocr_text_len": 1528
    },
    {
      "block_id": "6CNL-EGY6-A77",
      "page": 7,
      "file": "block_6CNL-EGY6-A77.png",
      "size_kb": 101.3,
      "crop_px": [
        9255,
        27,
        11053,
        6530
      ],
      "render_size": [
        436,
        1565
      ],
      "block_type": "image",
      "ocr_label": "Спецификация перемычек -1-го этажа на отметке -3,750. Содержит маркировку, эскиз",
      "ocr_text_len": 1619
    },
    {
      "block_id": "9Q3D-CHGG-L99",
      "page": 7,
      "file": "block_9Q3D-CHGG-L99.png",
      "size_kb": 87.1,
      "crop_px": [
        341,
        5444,
        1245,
        6710
      ],
      "render_size": [
        1077,
        1500
      ],
      "block_type": "image",
      "ocr_label": "Чертеж узла В в масштабе 1:50, представляющий конструктивное решение проема с пе",
      "ocr_text_len": 1152
    },
    {
      "block_id": "9KLF-NG4V-HHD",
      "page": 7,
      "file": "block_9KLF-NG4V-HHD.png",
      "size_kb": 119.7,
      "crop_px": [
        307,
        4337,
        1051,
        5412
      ],
      "render_size": [
        1045,
        1500
      ],
      "block_type": "image",
      "ocr_label": "Узел Б в масштабе 1:50, относящийся к разделу КЖ (конструкции железобетонные), с",
      "ocr_text_len": 1176
    },
    {
      "block_id": "7GKT-PC9E-7WD",
      "page": 7,
      "file": "block_7GKT-PC9E-7WD.png",
      "size_kb": 122.3,
      "crop_px": [
        271,
        3087,
        1075,
        4317
      ],
      "render_size": [
        988,
        1500
      ],
      "block_type": "image",
      "ocr_label": "Чертеж конструктивного узла (Узел А) в масштабе 1:50, относящийся к разделу КЖ (",
      "ocr_text_len": 1204
    },
    {
      "block_id": "AAMQ-ENV9-MN9",
      "page": 7,
      "file": "block_AAMQ-ENV9-MN9.png",
      "size_kb": 118.1,
      "crop_px": [
        8243,
        5342,
        9213,
        6494
      ],
      "render_size": [
        1267,
        1500
      ],
      "block_type": "image",
      "ocr_label": "Чертеж фрагмента стены с дверным проемом, обозначенный как 'Вид 8 (1:50)'. На че",
      "ocr_text_len": 1622
    },
    {
      "block_id": "UNNA-VXEV-9PM",
      "page": 7,
      "file": "block_UNNA-VXEV-9PM.png",
      "size_kb": 147.6,
      "crop_px": [
        8111,
        4089,
        9213,
        5296
      ],
      "render_size": [
        1371,
        1500
      ],
      "block_type": "image",
      "ocr_label": "Чертеж фрагмента стены (Вид 7) в масштабе 1:50, вероятно, относящийся к разделу ",
      "ocr_text_len": 1538
    },
    {
      "block_id": "9K76-PFTX-L3L",
      "page": 7,
      "file": "block_9K76-PFTX-L3L.png",
      "size_kb": 183.3,
      "crop_px": [
        7893,
        2753,
        9249,
        4061
      ],
      "render_size": [
        1500,
        1448
      ],
      "block_type": "image",
      "ocr_label": "Чертеж фрагмента фасада (Вид 6) в масштабе 1:50, отображающий раскладку стеновых",
      "ocr_text_len": 1381
    },
    {
      "block_id": "99NU-Y969-6AP",
      "page": 7,
      "file": "block_99NU-Y969-6AP.png",
      "size_kb": 102.9,
      "crop_px": [
        6621,
        95,
        7665,
        1493
      ],
      "render_size": [
        1125,
        1500
      ],
      "block_type": "image",
      "ocr_label": "Чертеж узла или фрагмента разреза (Вид 3) в масштабе 1:50, вероятно относящийся ",
      "ocr_text_len": 1574
    },
    {
      "block_id": "9LMR-4J69-R66",
      "page": 7,
      "file": "block_9LMR-4J69-R66.png",
      "size_kb": 127.0,
      "crop_px": [
        7613,
        55,
        9221,
        1421
      ],
      "render_size": [
        1500,
        1277
      ],
      "block_type": "image",
      "ocr_label": "Чертеж фрагмента стены (Вид 4) в масштабе 1:50, вероятно, раздел АР или КР, с ук",
      "ocr_text_len": 1718
    },
    {
      "block_id": "4GGJ-WA6Q-7QE",
      "page": 7,
      "file": "block_4GGJ-WA6Q-7QE.png",
      "size_kb": 131.5,
      "crop_px": [
        6631,
        1431,
        9241,
        2741
      ],
      "render_size": [
        1500,
        758
      ],
      "block_type": "image",
      "ocr_label": "Чертеж фрагмента стены (Вид 5) в масштабе 1:50 с указанием расположения технолог",
      "ocr_text_len": 1742
    },
    {
      "block_id": "6T4T-F4WR-P7U",
      "page": 7,
      "file": "block_6T4T-F4WR-P7U.png",
      "size_kb": 1121.9,
      "crop_px": [
        199,
        0,
        7679,
        6722
      ],
      "render_size": [
        1800,
        1616
      ],
      "block_type": "image",
      "ocr_label": "Чертежи планов на отм. -3,750: основной архитектурно-строительный план и план ин",
      "ocr_text_len": 1637
    },
    {
      "block_id": "7WEM-KHAC-CUP",
      "page": 8,
      "file": "block_7WEM-KHAC-CUP.png",
      "size_kb": 192.2,
      "crop_px": [
        3343,
        109,
        5287,
        2097
      ],
      "render_size": [
        1468,
        1500
      ],
      "block_type": "image",
      "ocr_label": "Чертеж узла примыкания внутренней кирпичной перегородки к перекрытию в масштабе ",
      "ocr_text_len": 1736
    },
    {
      "block_id": "96VX-QAXL-FNE",
      "page": 8,
      "file": "block_96VX-QAXL-FNE.png",
      "size_kb": 156.9,
      "crop_px": [
        1325,
        119,
        3835,
        2261
      ],
      "render_size": [
        1500,
        1282
      ],
      "block_type": "image",
      "ocr_label": "Чертеж узла примыкания внутренней кирпичной перегородки к монолитной стене или к",
      "ocr_text_len": 1526
    },
    {
      "block_id": "6TE3-J3XJ-33C",
      "page": 8,
      "file": "block_6TE3-J3XJ-33C.png",
      "size_kb": 43.3,
      "crop_px": [
        1563,
        2465,
        2605,
        3471
      ],
      "render_size": [
        1500,
        1449
      ],
      "block_type": "image",
      "ocr_label": "Схема раскладки блоков (первый ряд) Г-образного фрагмента стены. Чертеж содержит",
      "ocr_text_len": 924
    },
    {
      "block_id": "7NTH-WGTR-QQL",
      "page": 8,
      "file": "block_7NTH-WGTR-QQL.png",
      "size_kb": 38.7,
      "crop_px": [
        2931,
        2455,
        4053,
        3521
      ],
      "render_size": [
        1500,
        1426
      ],
      "block_type": "image",
      "ocr_label": "Схема раскладки блоков или элементов конструкции Г-образной формы, обозначенная ",
      "ocr_text_len": 930
    },
    {
      "block_id": "6NKH-RWRY-X7W",
      "page": 8,
      "file": "block_6NKH-RWRY-X7W.png",
      "size_kb": 41.0,
      "crop_px": [
        1749,
        3739,
        2903,
        4785
      ],
      "render_size": [
        1500,
        1362
      ],
      "block_type": "image",
      "ocr_label": "Фрагмент чертежа (вероятно, КЖ или АР), отображающий схему раскладки блоков или ",
      "ocr_text_len": 977
    },
    {
      "block_id": "64VP-VEP7-LYD",
      "page": 8,
      "file": "block_64VP-VEP7-LYD.png",
      "size_kb": 37.7,
      "crop_px": [
        661,
        3683,
        1659,
        4831
      ],
      "render_size": [
        1308,
        1500
      ],
      "block_type": "image",
      "ocr_label": "Схема Т-образной перевязки блоков первого ряда кладки. Чертеж содержит геометрич",
      "ocr_text_len": 920
    },
    {
      "block_id": "ACNR-KHHK-NPF",
      "page": 8,
      "file": "block_ACNR-KHHK-NPF.png",
      "size_kb": 65.8,
      "crop_px": [
        3003,
        3885,
        4089,
        4751
      ],
      "render_size": [
        1500,
        1201
      ],
      "block_type": "image",
      "ocr_label": "Аксонометрическая схема (изометрия) узла кирпичной или блочной кладки. Чертеж де",
      "ocr_text_len": 922
    },
    {
      "block_id": "9DAF-P9CV-VXC",
      "page": 9,
      "file": "block_9DAF-P9CV-VXC.png",
      "size_kb": 126.0,
      "crop_px": [
        7728,
        2957,
        9336,
        4177
      ],
      "render_size": [
        1500,
        1142
      ],
      "block_type": "image",
      "ocr_label": "Чертеж узла отделки стыка кладки и пилона. Относится к разделу АР (Архитектурные",
      "ocr_text_len": 1361
    },
    {
      "block_id": "4MM7-7UK9-WEX",
      "page": 9,
      "file": "block_4MM7-7UK9-WEX.png",
      "size_kb": 111.3,
      "crop_px": [
        8008,
        1639,
        9748,
        2655
      ],
      "render_size": [
        1500,
        882
      ],
      "block_type": "image",
      "ocr_label": "Чертеж узла заделки отверстий воздуховодов в стенах. Относится к разделу ОВ (Ото",
      "ocr_text_len": 1368
    },
    {
      "block_id": "6QVH-PUQN-UAH",
      "page": 9,
      "file": "block_6QVH-PUQN-UAH.png",
      "size_kb": 203.3,
      "crop_px": [
        7652,
        279,
        9326,
        1585
      ],
      "render_size": [
        1500,
        1174
      ],
      "block_type": "image",
      "ocr_label": "Чертеж узла заделки отверстий систем вентиляции (ОВ) в плите перекрытия. Относит",
      "ocr_text_len": 1511
    },
    {
      "block_id": "6MJ4-6F7H-7PU",
      "page": 9,
      "file": "block_6MJ4-6F7H-7PU.png",
      "size_kb": 143.4,
      "crop_px": [
        5950,
        275,
        7572,
        1525
      ],
      "render_size": [
        1500,
        1160
      ],
      "block_type": "image",
      "ocr_label": "Чертеж узла заделки инженерных отверстий в стенах. Относится к разделу АР (архит",
      "ocr_text_len": 1593
    },
    {
      "block_id": "A6XC-NQKF-MQQ",
      "page": 9,
      "file": "block_A6XC-NQKF-MQQ.png",
      "size_kb": 76.5,
      "crop_px": [
        5868,
        1645,
        7666,
        2513
      ],
      "render_size": [
        1500,
        732
      ],
      "block_type": "image",
      "ocr_label": "Чертеж узла прохода коммуникаций через стену (разрез К-К), относящийся к разделу",
      "ocr_text_len": 1354
    },
    {
      "block_id": "LE4G-YX3J-N69",
      "page": 9,
      "file": "block_LE4G-YX3J-N69.png",
      "size_kb": 188.9,
      "crop_px": [
        4007,
        165,
        5728,
        2619
      ],
      "render_size": [
        1056,
        1500
      ],
      "block_type": "image",
      "ocr_label": "Чертеж узла примыкания газобетонной кладки к железобетонной стене, разрез А-А. В",
      "ocr_text_len": 1349
    },
    {
      "block_id": "9FR7-E9AA-AC3",
      "page": 9,
      "file": "block_9FR7-E9AA-AC3.png",
      "size_kb": 144.5,
      "crop_px": [
        5048,
        2935,
        7424,
        4443
      ],
      "render_size": [
        1500,
        956
      ],
      "block_type": "image",
      "ocr_label": "Чертеж узла В-В: верхний узел крепления кладки из газобетонных блоков к железобе",
      "ocr_text_len": 1750
    },
    {
      "block_id": "4CPM-4JC9-GFD",
      "page": 9,
      "file": "block_4CPM-4JC9-GFD.png",
      "size_kb": 80.8,
      "crop_px": [
        4795,
        4509,
        7556,
        5517
      ],
      "render_size": [
        1500,
        554
      ],
      "block_type": "image",
      "ocr_label": "Чертеж узла Г-Г, демонстрирующий конструкцию стены из газобетонных блоков с мета",
      "ocr_text_len": 1535
    },
    {
      "block_id": "99AJ-7ACC-RLC",
      "page": 9,
      "file": "block_99AJ-7ACC-RLC.png",
      "size_kb": 76.7,
      "crop_px": [
        5252,
        5573,
        7016,
        6857
      ],
      "render_size": [
        1500,
        1096
      ],
      "block_type": "image",
      "ocr_label": "Чертеж узла перевязки поперечной перегородки из газобетонных блоков. Относится к",
      "ocr_text_len": 1214
    },
    {
      "block_id": "649N-3UKW-6PP",
      "page": 9,
      "file": "block_649N-3UKW-6PP.png",
      "size_kb": 191.2,
      "crop_px": [
        2309,
        2791,
        4875,
        6919
      ],
      "render_size": [
        935,
        1500
      ],
      "block_type": "image",
      "ocr_label": "Разрез Б-Б узла примыкания перегородки из газобетонных блоков к железобетонной с",
      "ocr_text_len": 1786
    },
    {
      "block_id": "67CP-PH4X-7E6",
      "page": 9,
      "file": "block_67CP-PH4X-7E6.png",
      "size_kb": 122.1,
      "crop_px": [
        403,
        2869,
        2139,
        4281
      ],
      "render_size": [
        1500,
        1223
      ],
      "block_type": "image",
      "ocr_label": "Чертеж узла соединения заплечика кладки с железобетонной стеной. Относится к раз",
      "ocr_text_len": 1436
    },
    {
      "block_id": "9A96-UAF3-XT9",
      "page": 9,
      "file": "block_9A96-UAF3-XT9.png",
      "size_kb": 168.3,
      "crop_px": [
        303,
        147,
        2015,
        2213
      ],
      "render_size": [
        1245,
        1500
      ],
      "block_type": "image",
      "ocr_label": "Чертеж опорного узла внутренней кладки из газобетонных блоков на железобетонную ",
      "ocr_text_len": 1619
    },
    {
      "block_id": "6Q9A-EWC4-MNG",
      "page": 9,
      "file": "block_6Q9A-EWC4-MNG.png",
      "size_kb": 122.4,
      "crop_px": [
        2081,
        157,
        3939,
        1349
      ],
      "render_size": [
        1500,
        968
      ],
      "block_type": "image",
      "ocr_label": "Узел крепления кладки из ячеистых блоков к железобетонной стене. Чертеж относитс",
      "ocr_text_len": 1443
    },
    {
      "block_id": "9NMY-WAML-KWD",
      "page": 9,
      "file": "block_9NMY-WAML-KWD.png",
      "size_kb": 103.8,
      "crop_px": [
        2097,
        1465,
        3887,
        2447
      ],
      "render_size": [
        1500,
        830
      ],
      "block_type": "image",
      "ocr_label": "Узел крепления кладки из ячеистых блоков к железобетонной стене. Чертеж относитс",
      "ocr_text_len": 1465
    },
    {
      "block_id": "7CKE-93KV-PP4",
      "page": 9,
      "file": "block_7CKE-93KV-PP4.png",
      "size_kb": 67.2,
      "crop_px": [
        1593,
        4571,
        2391,
        5435
      ],
      "render_size": [
        1388,
        1500
      ],
      "block_type": "image",
      "ocr_label": "Чертеж детали 'Скоба С1'. Вероятно, относится к разделу КМ/КЖ или АР в составе р",
      "ocr_text_len": 986
    },
    {
      "block_id": "7KYG-6EHV-NRU",
      "page": 9,
      "file": "block_7KYG-6EHV-NRU.png",
      "size_kb": 60.3,
      "crop_px": [
        1667,
        5435,
        2285,
        6325
      ],
      "render_size": [
        1050,
        1500
      ],
      "block_type": "image",
      "ocr_label": "Чертеж детали 'Скоба С2'. Вероятно, относится к разделу КМ/КЖ (конструктивные ре",
      "ocr_text_len": 977
    },
    {
      "block_id": "ACUL-E4AF-PHF",
      "page": 9,
      "file": "block_ACUL-E4AF-PHF.png",
      "size_kb": 36.4,
      "crop_px": [
        311,
        5633,
        1537,
        6373
      ],
      "render_size": [
        1500,
        914
      ],
      "block_type": "image",
      "ocr_label": "Чертеж изделия «Анкерная пластина С1», вероятно, относящийся к разделу КЖ или КМ",
      "ocr_text_len": 1087
    },
    {
      "block_id": "94KV-DM3Y-FE6",
      "page": 9,
      "file": "block_94KV-DM3Y-FE6.png",
      "size_kb": 69.7,
      "crop_px": [
        261,
        4383,
        1511,
        5501
      ],
      "render_size": [
        1500,
        1344
      ],
      "block_type": "image",
      "ocr_label": "Чертеж узла крепления (деталь уголка) для верхнего крепления внутренней кладки. ",
      "ocr_text_len": 1148
    },
    {
      "block_id": "EYEF-4VRX-JCN",
      "page": 10,
      "file": "block_EYEF-4VRX-JCN.png",
      "size_kb": 153.0,
      "crop_px": [
        3817,
        57,
        5530,
        1297
      ],
      "render_size": [
        1500,
        1090
      ],
      "block_type": "image",
      "ocr_label": "Сводная спецификация перемычек раздела 133/23-ГК-АР2, стадия РД (судя по детализ",
      "ocr_text_len": 1378
    },
    {
      "block_id": "6AJR-4YH6-YCT",
      "page": 10,
      "file": "block_6AJR-4YH6-YCT.png",
      "size_kb": 130.3,
      "crop_px": [
        1999,
        49,
        3755,
        6735
      ],
      "render_size": [
        426,
        1609
      ],
      "block_type": "image",
      "ocr_label": "Сводная спецификация перемычек раздела 133/23-ГК-АР2. Документация стадии АР (Ар",
      "ocr_text_len": 1734
    },
    {
      "block_id": "4CAP-QTLY-6GJ",
      "page": 10,
      "file": "block_4CAP-QTLY-6GJ.png",
      "size_kb": 115.6,
      "crop_px": [
        291,
        61,
        1999,
        6949
      ],
      "render_size": [
        414,
        1658
      ],
      "block_type": "image",
      "ocr_label": "Сводная спецификация перемычек раздела 133/23-ГК-АР2. Представлены чертежи и пар",
      "ocr_text_len": 1698
    },
    {
      "block_id": "7CMG-L4C4-939",
      "page": 10,
      "file": "block_7CMG-L4C4-939.png",
      "size_kb": 150.5,
      "crop_px": [
        3861,
        5173,
        5500,
        6539
      ],
      "render_size": [
        1500,
        1253
      ],
      "block_type": "image",
      "ocr_label": "Схема установки перемычек при креплении к железобетонным конструкциям. Чертеж со",
      "ocr_text_len": 1576
    },
    {
      "block_id": "6KCM-XXP9-47U",
      "page": 11,
      "file": "block_6KCM-XXP9-47U.png",
      "size_kb": 266.7,
      "crop_px": [
        211,
        69,
        5406,
        4028
      ],
      "render_size": [
        1500,
        1145
      ],
      "block_type": "image",
      "ocr_label": "План -2 этажа. Чертеж содержит архитектурно-строительные решения подземного уров",
      "ocr_text_len": 1536
    },
    {
      "block_id": "WY9X-W7HE-PUM",
      "page": 12,
      "file": "block_WY9X-W7HE-PUM.png",
      "size_kb": 769.4,
      "crop_px": [
        277,
        57,
        3545,
        5838
      ],
      "render_size": [
        850,
        1500
      ],
      "block_type": "image",
      "ocr_label": "План -1 этажа здания с указанием противопожарных преград. На чертеже выделены зо",
      "ocr_text_len": 1303
    }
  ],
  "total_expected": 55,
  "errors": 0
}