{
  "batch_id": 64,
  "project_id": "133-23-ГК-АИ1 18.02.2026",
  "timestamp": "2026-03-13T00:00:00",
  "block_analyses": [
    {
      "block_id": "633J-79FF-KNQ",
      "page": 58,
      "label": "План заполнения дверных проёмов МОП 15 этажа",
      "sheet_type": "door_schedule",
      "summary": "План МОП 15 этажа в масштабе 1:100, оси 1-3/5-7, В-Д. Показаны 4 помещения (1501–1504), три лифтовые шахты (СА-4), лестничные клетки ЛК-16 и ЛК-13. Нанесены марки дверных блоков с огнестойкостью (ДВ14-1Л EI30, ДВ7-2П EIWS60, ДВ20-1Л EIWS60, ДВ25-1П EI60, ДВ7-2А EIWS60, ДВ14-1П EI30), вентиляционные решётки РВ-С22, РВ-С23, РВ-С25, РВ-С16, РВ-С19, инженерные ниши (ОВ, ЭОМ, СС, ЗОМ ППУ, В1, В1П, Т11, Т21). Отметки ЧП: +49,950 (помещения 1501, 1503, 1504), +51,150 (ЛЛК 1502).",
      "key_values_read": [
        "ДВ14-1Л EI30, ширина проёма 850 мм",
        "ДВ7-2П EIWS60",
        "ДВ20-1Л EIWS60",
        "ДВ25-1П EI60",
        "ДВ7-2А EIWS60",
        "ДВ14-1П EI30",
        "ДВ2-5-1П EI60 (нижняя часть)",
        "РВ-С23 (верхняя зона, пом. 1504)",
        "РВ-С22 (верхняя зона, пом. 1504)",
        "РВ-С25 (зона ПБЗ)",
        "РВ-С16 (пом. 1503)",
        "РВ-С19 (пом. 1503)",
        "+49,950, +51,150",
        "Площадь 1501 = 21,2 м²",
        "Площадь 1502 = 29,0 м²",
        "Площадь 1504 = 14,0 м²"
      ],
      "findings": [
        {
          "id": "G-001",
          "severity": "РЕКОМЕНДАТЕЛЬНОЕ",
          "category": "documentation",
          "finding": "Вентиляционная решётка РВ-С20 (250×600 мм, 0,2 м²) присутствует в спецификации вент.решёток 15 этажа (1 шт.), однако метка РВ-С20 не обнаружена на чертеже плана заполнения дверных проёмов МОП 15 этажа. Шесть других марок (РВ-С16, РВ-С19, РВ-С22, РВ-С23, РВ-С25) идентифицированы на чертеже. Необходима проверка наличия и правильности нанесения обозначения РВ-С20.",
          "norm": null,
          "norm_quote": null,
          "norm_confidence": 0.0,
          "block_evidence": "block_633J-79FF-KNQ.png",
          "value_found": "РВ-С16, РВ-С19, РВ-С22, РВ-С23, РВ-С25 — видны на чертеже; РВ-С20 — не обнаружена"
        }
      ]
    }
  ],
  "items_verified_from_stage_01": []
}
