{
  "batch_id": 86,
  "project_id": "133-23-ГК-АИ1 18.02.2026",
  "timestamp": "2026-03-13T12:00:00",
  "block_analyses": [
    {
      "block_id": "9K6K-7JAA-A3T",
      "page": 78,
      "label": "Развёртка стены МОП первого этажа — Вид 14 (1:50)",
      "sheet_type": "wall_elevation",
      "summary": "Развёртка стены МОП первого этажа, общая длина 9545 мм. В левой части — зона подвесных светильников С4/С5 с многоуровневым подвесом от +4,200. По центру — декоративная панель О-1 с проёмом О-12 и оборудованием СО-1 (на высоте ~360 мм от пола). Справа — панель О-5.1 с розеткой 220V IP65. Уровень чистового потолка +4,200, низ плиты +4,600.",
      "key_values_read": ["+4,200 чистовой потолок", "+4,600 низ плиты", "9545 общая длина", "Розетка 220V IP65", "С4, С5 подвесные светильники", "СО-1", "О-1, О-12, О-5.1", "высота подвеса светильников: 100, 100, 100, 200, 300, 300, 300, 300, 300, 500 мм (от потолка)"],
      "findings": [
        {
          "id": "G-001",
          "severity": "РЕКОМЕНДАТЕЛЬНОЕ",
          "category": "lighting",
          "finding": "Для светильников С4 и С5 показаны многочисленные уровни подвеса (от 100 до 500 мм от потолка) без ссылки на тип светильника и спецификацию. Соответствие типов С4/С5 разделу ЭОМ не верифицировано по данному чертежу.",
          "norm": "Проверить по смежным (ЭОМ)",
          "norm_quote": null,
          "norm_confidence": 0.0,
          "block_evidence": "block_9K6K-7JAA-A3T.png",
          "value_found": "С4, С5 — уровни подвеса 100–500 мм от уровня +4,200"
        },
        {
          "id": "G-002",
          "severity": "РЕКОМЕНДАТЕЛЬНОЕ",
          "category": "walls",
          "finding": "Розетка 220V IP65 установлена в МОП первого этажа на высоте ~300 мм от пола. Степень защиты IP65 (защита от струй воды) применяется в зонах возможного попадания воды. Для сухого МОП достаточно IP44. Необходимо уточнить обоснование выбора IP65.",
          "norm": "ГОСТ 14254-2015 (IEC 60529), классификация IP",
          "norm_quote": null,
          "norm_confidence": 0.6,
          "block_evidence": "block_9K6K-7JAA-A3T.png",
          "value_found": "Розетка 220V, IP65 (на стене О-5.1, h≈300 мм от пола)"
        }
      ]
    },
    {
      "block_id": "96M6-FRWF-AUW",
      "page": 78,
      "label": "Развёртка стены МОП с арочным входом — Вид 13 (1:50)",
      "sheet_type": "wall_elevation",
      "summary": "Развёртка стены МОП, общая длина 17600 мм. Слева — арочный дверной проём высотой ~4150 мм с декоративной аркой. По всей стене чередуются панели О-5.1 на различных уровнях потолков (+4,000, +4,050, +4,100, +4,150). Справа — зона подвесных светильников С2, С3, С4, С5. Инженерное оборудование: сенсорная кнопка выхода AXI, светильник эвакуационный SCREEN WALL II, извещатель пожарный ручной адресный, кнопка экстренной разблокировки (у пола). Уровень чистового потолка переменный от +4,000 до +4,150.",
      "key_values_read": ["17600 общая длина", "+4,150 чистовой потолок (макс.)", "+4,000 чистовой потолок (мин.)", "SCREEN WALL II эвакуационный", "сенсорная кнопка выхода AXI", "извещатель пожарный ручной адресный", "кнопка экстренной разблокировки", "С2, С3, С4, С5"],
      "findings": [
        {
          "id": "G-003",
          "severity": "ЭКСПЛУАТАЦИОННОЕ",
          "category": "documentation",
          "finding": "Светильник эвакуационный настенного типа SCREEN WALL II показан с выноской в верхней части чертежа у уровня потолка (~+4,150). Настенные эвакуационные световые указатели при задымлении должны оставаться видимыми в нижней зоне. Слишком высокое размещение (~4,15 м) снижает эффективность при задымлении по сравнению с рекомендуемым диапазоном 2,0–2,5 м.",
          "norm": "СП 3.13130.2009, п.5.3",
          "norm_quote": "Световые указатели «Выход» следует устанавливать: у каждого эвакуационного выхода, предназначенного для эвакуации людей, на высоте не менее 2 м от уровня пола до нижнего края светильника.",
          "norm_confidence": 0.75,
          "block_evidence": "block_96M6-FRWF-AUW.png",
          "value_found": "SCREEN WALL II — выноска от уровня ~+4,150"
        }
      ]
    },
    {
      "block_id": "A9HC-PTV3-D4U",
      "page": 78,
      "label": "Развёртка стены с противопожарными дверями — Вид 17 (1:50)",
      "sheet_type": "wall_elevation",
      "summary": "Развёртка стены МОП, общая длина 6940 мм. Две противопожарные двери ДВ26-1Л/П EI30, высота проёма 2400 мм, ширина 820 мм каждая. Панели О-5.1 между и вокруг дверей. Уровни чистового потолка переменные: +4,000, +4,050, +4,100. Навигационные элементы СН1, СН2 с радиальными привязками (синие размеры). Потолочная камера. Ниша 50 мм в правой части.",
      "key_values_read": ["6940 общая длина", "ДВ26-1Л EI30, ДВ26-1П EI30", "высота проёма 2400 мм", "ширина проёма 820 мм", "СН1, СН2 навигация", "ниша 50 мм", "+4,000 / +4,050 / +4,100 уровни потолков"],
      "findings": [
        {
          "id": "G-004",
          "severity": "РЕКОМЕНДАТЕЛЬНОЕ",
          "category": "documentation",
          "finding": "На чертеже указано примечание: «Условные границы навигации. Тип крепления и точные привязки см. раздел РД по внутренней навигации». Ссылка на отдельный раздел РД по навигации означает неполноту данного чертежа. Необходимо убедиться, что раздел РД по навигации входит в состав проектной документации и передан на проверку.",
          "norm": null,
          "norm_quote": null,
          "norm_confidence": 0.0,
          "block_evidence": "block_A9HC-PTV3-D4U.png",
          "value_found": "Примечание на чертеже: «Условные границы навигации. Тип крепления и точные привязки см. раздел РД по внутренней навигации»"
        }
      ]
    },
    {
      "block_id": "6MEM-D7JN-3PA",
      "page": 78,
      "label": "Развёртка стены с арочным дверным проёмом — Вид 25 (1:50)",
      "sheet_type": "wall_elevation",
      "summary": "Развёртка стены МОП с арочным дверным блоком ДВ7-1Л и навигационными элементами СН2. Общая ширина 2505 мм. Отделка: О-1 (серая рейка), О-4, О-6 (арочное обрамление). Потолочная камера П1 на уровне +4,150. Высота проёма до арки ~2100–2400 мм. Чистовой потолок +4,150.",
      "key_values_read": ["2505 общая ширина", "ДВ7-1Л", "+4,150 чистовой потолок", "+2,400 верхняя отметка двери", "+2,100 нижняя отметка над дверью", "СН2 навигация", "П1, ПЛ1", "О-1, О-4, О-6"],
      "findings": []
    },
    {
      "block_id": "7KMC-LTF7-AU4",
      "page": 78,
      "label": "Развёртка длинной стены МОП с лифтовыми дверями — Вид 24 (1:50)",
      "sheet_type": "wall_elevation",
      "summary": "Развёртка длинной стены МОП, общая длина 13380 мм. Слева — двери лифтовых шахт ЛК-17 и ЛК-18 (высота 2800 мм). Центр — декоративная вертикальная панель ПС3 (рейки). Правая часть — зона с переменными уровнями потолков (+4,000–+4,150) и панелями О-5.1. Эвакуационный указатель SIGN WALL II «ПК» в верхней части левой зоны (~+4,150). Оповещатель световой «Направление к выходу» (красный блок). Потолочная камера в правой части.",
      "key_values_read": ["13380 общая длина", "ЛК-17, ЛК-18", "высота дверей ЛК 2800 мм", "SIGN WALL II ПК", "оповещатель световой «Направление к выходу»", "+4,000/+4,050/+4,100/+4,150 уровни потолков", "+3,950 отметка справа", "ПС3"],
      "findings": [
        {
          "id": "G-005",
          "severity": "ЭКСПЛУАТАЦИОННОЕ",
          "category": "documentation",
          "finding": "Указатель настенного типа SIGN WALL II «ПК» расположен у потолка (~+4,150 м). При этом оповещатель световой «Направление к выходу» размещён ниже (красный блок на чертеже на высоте ~+3,950-4,000). Высотные привязки для эвакуационных указателей на чертеже не проставлены (размеры в синем цвете отсутствуют для этих элементов), что не позволяет верифицировать соответствие требованиям.",
          "norm": "СП 3.13130.2009, п.5.3",
          "norm_quote": "Световые указатели «Выход» следует устанавливать на высоте не менее 2 м от уровня пола до нижнего края светильника.",
          "norm_confidence": 0.75,
          "block_evidence": "block_7KMC-LTF7-AU4.png",
          "value_found": "SIGN WALL II ПК — выноска у уровня потолка ~+4,150; высотные привязки для указателя не проставлены"
        }
      ]
    },
    {
      "block_id": "6WXY-9QC4-YCQ",
      "page": 78,
      "label": "Развёртка стены с противопожарной дверью — Вид 18 (1:50)",
      "sheet_type": "wall_elevation",
      "summary": "Развёртка стены с противопожарной дверью ДВ26-2Л EI30 (высота 2440 мм). Потолочная камера П1. Оповещатель (красный кружок) в верхней правой части стены. Общая ширина стены 1970 мм. Уровень чистового потолка +4,150, плита +4,600. Горизонтальные привязки: 455+615+800+85=1955 мм.",
      "key_values_read": ["ДВ26-2Л EI30", "высота двери 2440 мм", "1970 общая ширина", "+4,150 чистовой потолок", "+4,600 плита", "П1, ПЛ1, О-1"],
      "findings": [
        {
          "id": "G-006",
          "severity": "ПРОВЕРИТЬ ПО СМЕЖНЫМ",
          "category": "doors",
          "finding": "На развёртке Вид 18 дверь ДВ26-2Л EI30 показана в составе панели шириной ~800 мм (по горизонтальной размерной цепочке). Для противопожарных дверей на путях эвакуации ширина в свету должна составлять ≥900 мм (для обеспечения прохода). Необходимо сверить с ведомостью дверных заполнений для уточнения ширины в свету двери ДВ26-2Л.",
          "norm": "СП 1.13130.2020, п.4.2.5",
          "norm_quote": "Ширина эвакуационного выхода должна быть не менее 0,9 м.",
          "norm_confidence": 0.8,
          "block_evidence": "block_6WXY-9QC4-YCQ.png",
          "value_found": "ДВ26-2Л EI30, горизонтальная привязка 800 мм"
        }
      ]
    },
    {
      "block_id": "6FRJ-NKG9-DFF",
      "page": 78,
      "label": "Развёртка стены с арочной дверью и эвакуационным оборудованием — Вид 20 (1:50)",
      "sheet_type": "wall_elevation",
      "summary": "Развёртка стены МОП, ширина 2695 мм. Дверь ДВ7-1П с арочным верхом (высота 2700 мм, нижняя отметка начала арки +2,100). Оповещатель световой «Направление к выходу» расположен в зоне +2,100–+2,400 — соответствует норме. Указатель SIGN WALL II «ПК» на правой стене — в верхней части (~+4,150). РВ-С18 (вентиляционный клапан?) в потолочной зоне. Примечание о теневом профиле — завести отделку выше чистового потолка на 100 мм.",
      "key_values_read": ["2695 общая ширина", "ДВ7-1П", "высота двери 2700 мм", "+2,100 / +2,400 высоты", "+4,150 чистовой потолок", "+4,600 плита", "SIGN WALL II ПК (у потолка)", "оповещатель световой (~+2,100–+2,400)", "РВ-С18", "П1, ПЛ1, О-1"],
      "findings": [
        {
          "id": "G-007",
          "severity": "ЭКСПЛУАТАЦИОННОЕ",
          "category": "documentation",
          "finding": "Указатель настенного типа SIGN WALL II «ПК» (правая сторона Вид 20) размещён у потолка (~+4,150 м). На чертеже высотная привязка для данного указателя не проставлена. Эффективность эвакуационного указателя при задымлении снижается при размещении выше 2,5 м. Рекомендуется проверить высоту установки и обеспечить соответствие СП 3.13130.2009.",
          "norm": "СП 3.13130.2009, п.5.3",
          "norm_quote": "Световые указатели «Выход» следует устанавливать на высоте не менее 2 м от уровня пола до нижнего края светильника.",
          "norm_confidence": 0.75,
          "block_evidence": "block_6FRJ-NKG9-DFF.png",
          "value_found": "SIGN WALL II «ПК» — выноска к элементу в верхней части стены (~+4,150)"
        }
      ]
    },
    {
      "block_id": "6LH3-46HA-T7D",
      "page": 78,
      "label": "Развёртка стены с дверью ДВ26-3П — Вид 22 (1:50)",
      "sheet_type": "wall_elevation",
      "summary": "Развёртка стены, общая ширина по размерным цепочкам 660+700+1285+900+1520=5065 мм. Отделка панелями О-6 (основная часть стены) и О-1 (вертикальная полоса). Дверь ДВ26-3П с арочным верхом, высота 2400 мм, ширина проёма 900 мм. Плинтус ПЛ1 по всей длине. Высотная отметка только +0,000 — уровень чистового потолка на данном виде не указан.",
      "key_values_read": ["ДВ26-3П", "высота двери 2400 мм", "ширина проёма 900 мм", "+0,000", "О-6, О-1, ПЛ1"],
      "findings": [
        {
          "id": "G-008",
          "severity": "РЕКОМЕНДАТЕЛЬНОЕ",
          "category": "documentation",
          "finding": "На развёртке Вид 22 отсутствуют высотные отметки уровня чистового потолка. Указана только отметка +0,000 (уровень пола). Это не позволяет проверить высоту помещения в чистоте и соответствие нормативным требованиям по высоте МОП.",
          "norm": null,
          "norm_quote": null,
          "norm_confidence": 0.0,
          "block_evidence": "block_6LH3-46HA-T7D.png",
          "value_found": "Высотные отметки на чертеже: только +0,000"
        }
      ]
    },
    {
      "block_id": "7Y3F-TFNA-FWU",
      "page": 78,
      "label": "Развёртка стены помещения с сантехоборудованием — Вид 30 (1:50)",
      "sheet_type": "wall_elevation",
      "summary": "Развёртка стены технического/санитарного помещения. Отделка О-3 (плитка) в двух зонах. Оборудование: СО-2 (около +0,850), СП-11 (выключатель/смеситель). Коробка распределительная в нижней части (~h≈0,450 от пола). ПС5 — поручни или плинтусы на высотах +0,850 и +2,400. Подвесной потолок П4 на уровне +3,500. Высота помещения в чистоте 3500 мм. Общая ширина секций: 450+1045+1050+1490=4035 мм.",
      "key_values_read": ["П4 потолок на +3,500", "+3,500 чистовой потолок", "+4,600 плита", "СО-2", "СП-11", "коробка распределительная", "ПС5", "О-3 плитка", "+0,850 / +2,400 высоты элементов"],
      "findings": [
        {
          "id": "G-009",
          "severity": "КРИТИЧЕСКОЕ",
          "category": "walls",
          "finding": "Коробка распределительная (электрическая) расположена в помещении с плиточной отделкой и сантехническим оборудованием (мокрая зона). На чертеже отсутствует указание степени защиты (IP) коробки. Для электрооборудования в зонах с повышенной влажностью (зона 2-3 по ГОСТ Р 50571.7.701) требуется степень защиты не ниже IP44.",
          "norm": "СП 256.1325800.2016, п.15.1; ГОСТ Р 50571.7.701-2013",
          "norm_quote": null,
          "norm_confidence": 0.65,
          "block_evidence": "block_7Y3F-TFNA-FWU.png",
          "value_found": "Коробка распределительная — высота установки ~+0,450, без указания IP"
        }
      ]
    },
    {
      "block_id": "7WVL-NRU4-M9N",
      "page": 78,
      "label": "Развёртка стены санузла с инсталляцией — Вид 29 (1:50)",
      "sheet_type": "wall_elevation",
      "summary": "Развёртка стены санузла, ширина 1775 мм. Инсталляция СН4 с кнопкой смыва, смеситель/кран СП-12. Отделка: О-8 (верхняя зона), О-3 (средняя зона), О-7 (нижний пояс до +0,450). Поручни/рейки ПС5 на высотах +0,850 и +2,400. Подвесной потолок П4 на уровне +3,500. Примечание о теневом профиле — завести отделку на 100 мм выше чистового потолка. Высотные отметки: +0,000, +0,450, +0,850, +2,400, +3,500, +4,600.",
      "key_values_read": ["1775 ширина", "+3,500 чистовой потолок (П4)", "+4,600 плита", "СН4 инсталляция", "СП-12 смеситель", "ПС5", "О-7, О-3, О-8 отделка", "900 высота зоны О-8", "1540/1700 высота зон О-8/О-3"],
      "findings": [
        {
          "id": "G-010",
          "severity": "КРИТИЧЕСКОЕ",
          "category": "bathroom",
          "finding": "На развёртке стены санузла (Вид 29) отсутствует отметка о гидроизоляции — нет указания высоты заведения гидроизоляционного слоя на стены. Отделочные материалы О-7, О-3, О-8 нанесены начиная с отметки +0,000, однако требование по гидроизоляции стен санузла (заведение не менее 200 мм от пола) не отражено.",
          "norm": "СП 29.13330.2011, п.8.8",
          "norm_quote": "В санузлах жилых зданий гидроизоляцию следует предусматривать по всей площади пола и на стенах на высоту не менее 200 мм от уровня чистого пола.",
          "norm_confidence": 0.8,
          "block_evidence": "block_7WVL-NRU4-M9N.png",
          "value_found": "Развёртка стены санузла: отделка О-7 начинается с +0,000; отметки гидроизоляции отсутствуют"
        }
      ]
    }
  ],
  "items_verified_from_stage_01": []
}
